relations/__init__.py
relations/base.py
relations/cache.py
relations/descriptors.py
relations/interfaces.py
python_relations-0.1.0.post1.dist-info/LICENSE
python_relations-0.1.0.post1.dist-info/METADATA
python_relations-0.1.0.post1.dist-info/WHEEL
python_relations-0.1.0.post1.dist-info/top_level.txt
python_relations-0.1.0.post1.dist-info/RECORD
