Metadata-Version: 2.1
Name: python-relations
Version: 0.1.0.post1
Summary: A Python library for managing model relationships
Home-page: https://github.com/vistart/relations
Author: vistart
Classifier: Development Status :: 3 - Alpha
Classifier: Intended Audience :: Developers
Classifier: License :: OSI Approved :: MIT License
Classifier: Programming Language :: Python :: 3
Classifier: Programming Language :: Python :: 3.8
Classifier: Programming Language :: Python :: 3.9
Classifier: Programming Language :: Python :: 3.10
Classifier: Programming Language :: Python :: 3.11
Classifier: Programming Language :: Python :: 3.12
Classifier: Programming Language :: Python :: 3.13
Requires-Python: >=3.8
License-File: LICENSE
Requires-Dist: pydantic >=2.0.0
Requires-Dist: typing-extensions >=4.0.0
